themstates/__init__.py
themstates/themstates.py
themstates-1.0.0.dist-info/LICENSE
themstates-1.0.0.dist-info/METADATA
themstates-1.0.0.dist-info/WHEEL
themstates-1.0.0.dist-info/top_level.txt
themstates-1.0.0.dist-info/RECORD
