Metadata-Version: 2.1
Name: themstates
Version: 1.0.0
Summary: Simple and powerful state machine.
Home-page: https://github.com/kashifrazzaqui/themstates
Author: Kashif Razzaqui
Author-email: kashif.razzaqui@gmail.com
License: UNKNOWN
Platform: UNKNOWN
